canonical_imports/__init__.py
canonical_imports/__main__.py
canonical_imports-0.0.1.dist-info/METADATA
canonical_imports-0.0.1.dist-info/WHEEL
canonical_imports-0.0.1.dist-info/entry_points.txt
canonical_imports-0.0.1.dist-info/licenses/LICENSE.txt
canonical_imports-0.0.1.dist-info/RECORD
