Metadata-Version: 2.1
Name: canonical-imports
Version: 0.0.1
Summary: directly import everything from where it is defined
Project-URL: Documentation, https://github.com/unknown/canonical-imports#readme
Project-URL: Issues, https://github.com/unknown/canonical-imports/issues
Project-URL: Source, https://github.com/unknown/canonical-imports
Author-email: Frank Hoffmann <15r10nk@polarbit.de>
License-Expression: MIT
License-File: LICENSE.txt
Classifier: Development Status :: 4 - Beta
Classifier: Programming Language :: Python
Classifier: Programming Language :: Python :: 3.8
Classifier: Programming Language :: Python :: 3.9
Classifier: Programming Language :: Python :: 3.10
Classifier: Programming Language :: Python :: 3.11
Classifier: Programming Language :: Python :: 3.12
Classifier: Programming Language :: Python :: Implementation :: CPython
Classifier: Programming Language :: Python :: Implementation :: PyPy
Requires-Python: >=3.8
